[
  {
    "Source": "FireEyeHelix",
    "Product": "FireEye Helix",
    "EventName": null,
    "SecurityEventFieldName": "SourceUserName",
    "TransformationFunction": 0,
    "TransformationFunctionParam": "",
    "RawDataPrimaryFieldMatchTerm": "username",
    "RawDataPrimaryFieldComparisonType": 0,
    "RawDataSecondaryFieldMatchTerm": "",
    "RawDataSecondaryFieldComparisonType": 0,
    "RawDataThirdFieldMatchTerm": "",
    "RawDataThirdFieldComparisonType": 0,
    "IsArtifact": false,
    "ExtractionFunctionParam": "",
    "ExtractionFunction": 0,
    "CreationTimeUnixTimeInMs": 1623983029078,
    "ModificationTimeUnixTimeInMs": 1623983029078
  },
  {
    "Source": "FireEyeHelix",
    "Product": "FireEye Helix",
    "EventName": null,
    "SecurityEventFieldName": "DestinationUserName",
    "TransformationFunction": 0,
    "TransformationFunctionParam": "",
    "RawDataPrimaryFieldMatchTerm": "",
    "RawDataPrimaryFieldComparisonType": 0,
    "RawDataSecondaryFieldMatchTerm": "",
    "RawDataSecondaryFieldComparisonType": 0,
    "RawDataThirdFieldMatchTerm": "",
    "RawDataThirdFieldComparisonType": 0,
    "IsArtifact": false,
    "ExtractionFunctionParam": "",
    "ExtractionFunction": 0,
    "CreationTimeUnixTimeInMs": 1623983029078,
    "ModificationTimeUnixTimeInMs": 1623983029078
  },
  {
    "Source": "FireEyeHelix",
    "Product": "FireEye Helix",
    "EventName": null,
    "SecurityEventFieldName": "SourceHostName",
    "TransformationFunction": 0,
    "TransformationFunctionParam": "",
    "RawDataPrimaryFieldMatchTerm": "hostname",
    "RawDataPrimaryFieldComparisonType": 0,
    "RawDataSecondaryFieldMatchTerm": "",
    "RawDataSecondaryFieldComparisonType": 0,
    "RawDataThirdFieldMatchTerm": "",
    "RawDataThirdFieldComparisonType": 0,
    "IsArtifact": false,
    "ExtractionFunctionParam": "",
    "ExtractionFunction": 0,
    "CreationTimeUnixTimeInMs": 1623983029078,
    "ModificationTimeUnixTimeInMs": 1623983029078
  },
  {
    "Source": "FireEyeHelix",
    "Product": "FireEye Helix",
    "EventName": null,
    "SecurityEventFieldName": "DestinationHostName",
    "TransformationFunction": 0,
    "TransformationFunctionParam": "",
    "RawDataPrimaryFieldMatchTerm": "",
    "RawDataPrimaryFieldComparisonType": 0,
    "RawDataSecondaryFieldMatchTerm": "",
    "RawDataSecondaryFieldComparisonType": 0,
    "RawDataThirdFieldMatchTerm": "",
    "RawDataThirdFieldComparisonType": 0,
    "IsArtifact": false,
    "ExtractionFunctionParam": "",
    "ExtractionFunction": 0,
    "CreationTimeUnixTimeInMs": 1623983029078,
    "ModificationTimeUnixTimeInMs": 1623983029078
  },
  {
    "Source": "FireEyeHelix",
    "Product": "FireEye Helix",
    "EventName": null,
    "SecurityEventFieldName": "SourceDomain",
    "TransformationFunction": 0,
    "TransformationFunctionParam": "",
    "RawDataPrimaryFieldMatchTerm": "srcdomain",
    "RawDataPrimaryFieldComparisonType": 0,
    "RawDataSecondaryFieldMatchTerm": "",
    "RawDataSecondaryFieldComparisonType": 0,
    "RawDataThirdFieldMatchTerm": "",
    "RawDataThirdFieldComparisonType": 0,
    "IsArtifact": true,
    "ExtractionFunctionParam": "",
    "ExtractionFunction": 0,
    "CreationTimeUnixTimeInMs": 1623983029078,
    "ModificationTimeUnixTimeInMs": 1623983029078
  },
  {
    "Source": "FireEyeHelix",
    "Product": "FireEye Helix",
    "EventName": null,
    "SecurityEventFieldName": "DestinationDomain",
    "TransformationFunction": 0,
    "TransformationFunctionParam": "",
    "RawDataPrimaryFieldMatchTerm": "dstdomain",
    "RawDataPrimaryFieldComparisonType": 0,
    "RawDataSecondaryFieldMatchTerm": "",
    "RawDataSecondaryFieldComparisonType": 0,
    "RawDataThirdFieldMatchTerm": "",
    "RawDataThirdFieldComparisonType": 0,
    "IsArtifact": true,
    "ExtractionFunctionParam": "",
    "ExtractionFunction": 0,
    "CreationTimeUnixTimeInMs": 1623983029078,
    "ModificationTimeUnixTimeInMs": 1623983029078
  },
  {
    "Source": "FireEyeHelix",
    "Product": "FireEye Helix",
    "EventName": null,
    "SecurityEventFieldName": "SourceAddress",
    "TransformationFunction": 0,
    "TransformationFunctionParam": "",
    "RawDataPrimaryFieldMatchTerm": "srcipv4",
    "RawDataPrimaryFieldComparisonType": 0,
    "RawDataSecondaryFieldMatchTerm": "",
    "RawDataSecondaryFieldComparisonType": 0,
    "RawDataThirdFieldMatchTerm": "",
    "RawDataThirdFieldComparisonType": 0,
    "IsArtifact": false,
    "ExtractionFunctionParam": "",
    "ExtractionFunction": 0,
    "CreationTimeUnixTimeInMs": 1623983029078,
    "ModificationTimeUnixTimeInMs": 1623983029078
  },
  {
    "Source": "FireEyeHelix",
    "Product": "FireEye Helix",
    "EventName": null,
    "SecurityEventFieldName": "DestinationAddress",
    "TransformationFunction": 0,
    "TransformationFunctionParam": "",
    "RawDataPrimaryFieldMatchTerm": "dstipv4",
    "RawDataPrimaryFieldComparisonType": 0,
    "RawDataSecondaryFieldMatchTerm": "",
    "RawDataSecondaryFieldComparisonType": 0,
    "RawDataThirdFieldMatchTerm": "",
    "RawDataThirdFieldComparisonType": 0,
    "IsArtifact": false,
    "ExtractionFunctionParam": "",
    "ExtractionFunction": 0,
    "CreationTimeUnixTimeInMs": 1623983029078,
    "ModificationTimeUnixTimeInMs": 1623983029078
  },
  {
    "Source": "FireEyeHelix",
    "Product": "FireEye Helix",
    "EventName": null,
    "SecurityEventFieldName": "GenericEntity",
    "TransformationFunction": 0,
    "TransformationFunctionParam": "",
    "RawDataPrimaryFieldMatchTerm": "",
    "RawDataPrimaryFieldComparisonType": 0,
    "RawDataSecondaryFieldMatchTerm": "",
    "RawDataSecondaryFieldComparisonType": 0,
    "RawDataThirdFieldMatchTerm": "",
    "RawDataThirdFieldComparisonType": 0,
    "IsArtifact": false,
    "ExtractionFunctionParam": "",
    "ExtractionFunction": 0,
    "CreationTimeUnixTimeInMs": 1623983029078,
    "ModificationTimeUnixTimeInMs": 1623983029078
  },
  {
    "Source": "FireEyeHelix",
    "Product": "FireEye Helix",
    "EventName": null,
    "SecurityEventFieldName": "ThreatSignature",
    "TransformationFunction": 0,
    "TransformationFunctionParam": "",
    "RawDataPrimaryFieldMatchTerm": "",
    "RawDataPrimaryFieldComparisonType": 0,
    "RawDataSecondaryFieldMatchTerm": "",
    "RawDataSecondaryFieldComparisonType": 0,
    "RawDataThirdFieldMatchTerm": "",
    "RawDataThirdFieldComparisonType": 0,
    "IsArtifact": true,
    "ExtractionFunctionParam": "",
    "ExtractionFunction": 0,
    "CreationTimeUnixTimeInMs": 1623983029078,
    "ModificationTimeUnixTimeInMs": 1623983029078
  },
  {
    "Source": "FireEyeHelix",
    "Product": "FireEye Helix",
    "EventName": null,
    "SecurityEventFieldName": "ThreatCampaign",
    "TransformationFunction": 0,
    "TransformationFunctionParam": "",
    "RawDataPrimaryFieldMatchTerm": "",
    "RawDataPrimaryFieldComparisonType": 0,
    "RawDataSecondaryFieldMatchTerm": "",
    "RawDataSecondaryFieldComparisonType": 0,
    "RawDataThirdFieldMatchTerm": "",
    "RawDataThirdFieldComparisonType": 0,
    "IsArtifact": true,
    "ExtractionFunctionParam": "",
    "ExtractionFunction": 0,
    "CreationTimeUnixTimeInMs": 1623983029078,
    "ModificationTimeUnixTimeInMs": 1623983029078
  },
  {
    "Source": "FireEyeHelix",
    "Product": "FireEye Helix",
    "EventName": null,
    "SecurityEventFieldName": "ThreatActor",
    "TransformationFunction": 0,
    "TransformationFunctionParam": "",
    "RawDataPrimaryFieldMatchTerm": "",
    "RawDataPrimaryFieldComparisonType": 0,
    "RawDataSecondaryFieldMatchTerm": "",
    "RawDataSecondaryFieldComparisonType": 0,
    "RawDataThirdFieldMatchTerm": "",
    "RawDataThirdFieldComparisonType": 0,
    "IsArtifact": true,
    "ExtractionFunctionParam": "",
    "ExtractionFunction": 0,
    "CreationTimeUnixTimeInMs": 1623983029078,
    "ModificationTimeUnixTimeInMs": 1623983029078
  },
  {
    "Source": "FireEyeHelix",
    "Product": "FireEye Helix",
    "EventName": null,
    "SecurityEventFieldName": "CVE",
    "TransformationFunction": 0,
    "TransformationFunctionParam": "",
    "RawDataPrimaryFieldMatchTerm": "",
    "RawDataPrimaryFieldComparisonType": 0,
    "RawDataSecondaryFieldMatchTerm": "",
    "RawDataSecondaryFieldComparisonType": 0,
    "RawDataThirdFieldMatchTerm": "",
    "RawDataThirdFieldComparisonType": 0,
    "IsArtifact": true,
    "ExtractionFunctionParam": "",
    "ExtractionFunction": 0,
    "CreationTimeUnixTimeInMs": 1623983029078,
    "ModificationTimeUnixTimeInMs": 1623983029078
  },
  {
    "Source": "FireEyeHelix",
    "Product": "FireEye Helix",
    "EventName": null,
    "SecurityEventFieldName": "PhoneNumber",
    "TransformationFunction": 0,
    "TransformationFunctionParam": "",
    "RawDataPrimaryFieldMatchTerm": "",
    "RawDataPrimaryFieldComparisonType": 0,
    "RawDataSecondaryFieldMatchTerm": "",
    "RawDataSecondaryFieldComparisonType": 0,
    "RawDataThirdFieldMatchTerm": "",
    "RawDataThirdFieldComparisonType": 0,
    "IsArtifact": true,
    "ExtractionFunctionParam": "",
    "ExtractionFunction": 0,
    "CreationTimeUnixTimeInMs": 1623983029078,
    "ModificationTimeUnixTimeInMs": 1623983029078
  },
  {
    "Source": "FireEyeHelix",
    "Product": "FireEye Helix",
    "EventName": null,
    "SecurityEventFieldName": "CreditCard",
    "TransformationFunction": 0,
    "TransformationFunctionParam": "",
    "RawDataPrimaryFieldMatchTerm": "",
    "RawDataPrimaryFieldComparisonType": 0,
    "RawDataSecondaryFieldMatchTerm": "",
    "RawDataSecondaryFieldComparisonType": 0,
    "RawDataThirdFieldMatchTerm": "",
    "RawDataThirdFieldComparisonType": 0,
    "IsArtifact": true,
    "ExtractionFunctionParam": "",
    "ExtractionFunction": 0,
    "CreationTimeUnixTimeInMs": 1623983029078,
    "ModificationTimeUnixTimeInMs": 1623983029078
  },
  {
    "Source": "FireEyeHelix",
    "Product": "FireEye Helix",
    "EventName": null,
    "SecurityEventFieldName": "SourceMacAddress",
    "TransformationFunction": 0,
    "TransformationFunctionParam": "",
    "RawDataPrimaryFieldMatchTerm": "",
    "RawDataPrimaryFieldComparisonType": 0,
    "RawDataSecondaryFieldMatchTerm": "",
    "RawDataSecondaryFieldComparisonType": 0,
    "RawDataThirdFieldMatchTerm": "",
    "RawDataThirdFieldComparisonType": 0,
    "IsArtifact": false,
    "ExtractionFunctionParam": "",
    "ExtractionFunction": 0,
    "CreationTimeUnixTimeInMs": 1623983029078,
    "ModificationTimeUnixTimeInMs": 1623983029078
  },
  {
    "Source": "FireEyeHelix",
    "Product": "FireEye Helix",
    "EventName": null,
    "SecurityEventFieldName": "DestinationMacAddress",
    "TransformationFunction": 0,
    "TransformationFunctionParam": "",
    "RawDataPrimaryFieldMatchTerm": "",
    "RawDataPrimaryFieldComparisonType": 0,
    "RawDataSecondaryFieldMatchTerm": "",
    "RawDataSecondaryFieldComparisonType": 0,
    "RawDataThirdFieldMatchTerm": "",
    "RawDataThirdFieldComparisonType": 0,
    "IsArtifact": false,
    "ExtractionFunctionParam": "",
    "ExtractionFunction": 0,
    "CreationTimeUnixTimeInMs": 1623983029078,
    "ModificationTimeUnixTimeInMs": 1623983029078
  },
  {
    "Source": "FireEyeHelix",
    "Product": "FireEye Helix",
    "EventName": null,
    "SecurityEventFieldName": "Deployment",
    "TransformationFunction": 0,
    "TransformationFunctionParam": "",
    "RawDataPrimaryFieldMatchTerm": "",
    "RawDataPrimaryFieldComparisonType": 0,
    "RawDataSecondaryFieldMatchTerm": "",
    "RawDataSecondaryFieldComparisonType": 0,
    "RawDataThirdFieldMatchTerm": "",
    "RawDataThirdFieldComparisonType": 0,
    "IsArtifact": true,
    "ExtractionFunctionParam": "",
    "ExtractionFunction": 0,
    "CreationTimeUnixTimeInMs": 1623983029078,
    "ModificationTimeUnixTimeInMs": 1623983029078
  },
  {
    "Source": "FireEyeHelix",
    "Product": "FireEye Helix",
    "EventName": null,
    "SecurityEventFieldName": "USB",
    "TransformationFunction": 0,
    "TransformationFunctionParam": "",
    "RawDataPrimaryFieldMatchTerm": "",
    "RawDataPrimaryFieldComparisonType": 0,
    "RawDataSecondaryFieldMatchTerm": "",
    "RawDataSecondaryFieldComparisonType": 0,
    "RawDataThirdFieldMatchTerm": "",
    "RawDataThirdFieldComparisonType": 0,
    "IsArtifact": true,
    "ExtractionFunctionParam": "",
    "ExtractionFunction": 0,
    "CreationTimeUnixTimeInMs": 1623983029078,
    "ModificationTimeUnixTimeInMs": 1623983029078
  },
  {
    "Source": "FireEyeHelix",
    "Product": "FireEye Helix",
    "EventName": null,
    "SecurityEventFieldName": "EmailSubject",
    "TransformationFunction": 0,
    "TransformationFunctionParam": "",
    "RawDataPrimaryFieldMatchTerm": "",
    "RawDataPrimaryFieldComparisonType": 0,
    "RawDataSecondaryFieldMatchTerm": "",
    "RawDataSecondaryFieldComparisonType": 0,
    "RawDataThirdFieldMatchTerm": "",
    "RawDataThirdFieldComparisonType": 0,
    "IsArtifact": true,
    "ExtractionFunctionParam": "",
    "ExtractionFunction": 0,
    "CreationTimeUnixTimeInMs": 1623983029078,
    "ModificationTimeUnixTimeInMs": 1623983029078
  },
  {
    "Source": "FireEyeHelix",
    "Product": "FireEye Helix",
    "EventName": null,
    "SecurityEventFieldName": "FileHash",
    "TransformationFunction": 0,
    "TransformationFunctionParam": "",
    "RawDataPrimaryFieldMatchTerm": "",
    "RawDataPrimaryFieldComparisonType": 0,
    "RawDataSecondaryFieldMatchTerm": "",
    "RawDataSecondaryFieldComparisonType": 0,
    "RawDataThirdFieldMatchTerm": "",
    "RawDataThirdFieldComparisonType": 0,
    "IsArtifact": true,
    "ExtractionFunctionParam": "",
    "ExtractionFunction": 0,
    "CreationTimeUnixTimeInMs": 1623983029078,
    "ModificationTimeUnixTimeInMs": 1623983029078
  },
  {
    "Source": "FireEyeHelix",
    "Product": "FireEye Helix",
    "EventName": null,
    "SecurityEventFieldName": "FileName",
    "TransformationFunction": 0,
    "TransformationFunctionParam": "",
    "RawDataPrimaryFieldMatchTerm": "filename",
    "RawDataPrimaryFieldComparisonType": 0,
    "RawDataSecondaryFieldMatchTerm": "",
    "RawDataSecondaryFieldComparisonType": 0,
    "RawDataThirdFieldMatchTerm": "",
    "RawDataThirdFieldComparisonType": 0,
    "IsArtifact": true,
    "ExtractionFunctionParam": "",
    "ExtractionFunction": 0,
    "CreationTimeUnixTimeInMs": 1623983029078,
    "ModificationTimeUnixTimeInMs": 1623983029078
  },
  {
    "Source": "FireEyeHelix",
    "Product": "FireEye Helix",
    "EventName": null,
    "SecurityEventFieldName": "DestinationURL",
    "TransformationFunction": 0,
    "TransformationFunctionParam": "",
    "RawDataPrimaryFieldMatchTerm": "",
    "RawDataPrimaryFieldComparisonType": 0,
    "RawDataSecondaryFieldMatchTerm": "",
    "RawDataSecondaryFieldComparisonType": 0,
    "RawDataThirdFieldMatchTerm": "",
    "RawDataThirdFieldComparisonType": 0,
    "IsArtifact": true,
    "ExtractionFunctionParam": "",
    "ExtractionFunction": 0,
    "CreationTimeUnixTimeInMs": 1623983029078,
    "ModificationTimeUnixTimeInMs": 1623983029078
  },
  {
    "Source": "FireEyeHelix",
    "Product": "FireEye Helix",
    "EventName": null,
    "SecurityEventFieldName": "DestinationProcessName",
    "TransformationFunction": 0,
    "TransformationFunctionParam": "",
    "RawDataPrimaryFieldMatchTerm": "",
    "RawDataPrimaryFieldComparisonType": 0,
    "RawDataSecondaryFieldMatchTerm": "",
    "RawDataSecondaryFieldComparisonType": 0,
    "RawDataThirdFieldMatchTerm": "",
    "RawDataThirdFieldComparisonType": 0,
    "IsArtifact": true,
    "ExtractionFunctionParam": "",
    "ExtractionFunction": 0,
    "CreationTimeUnixTimeInMs": 1623983029078,
    "ModificationTimeUnixTimeInMs": 1623983029078
  },
  {
    "Source": "FireEyeHelix",
    "Product": "FireEye Helix",
    "EventName": null,
    "SecurityEventFieldName": "SourceProcessName",
    "TransformationFunction": 0,
    "TransformationFunctionParam": "",
    "RawDataPrimaryFieldMatchTerm": "",
    "RawDataPrimaryFieldComparisonType": 0,
    "RawDataSecondaryFieldMatchTerm": "",
    "RawDataSecondaryFieldComparisonType": 0,
    "RawDataThirdFieldMatchTerm": "",
    "RawDataThirdFieldComparisonType": 0,
    "IsArtifact": true,
    "ExtractionFunctionParam": "",
    "ExtractionFunction": 0,
    "CreationTimeUnixTimeInMs": 1623983029078,
    "ModificationTimeUnixTimeInMs": 1623983029078
  },
  {
    "Source": "FireEyeHelix",
    "Product": "FireEye Helix",
    "EventName": null,
    "SecurityEventFieldName": "StartTime",
    "TransformationFunction": 4,
    "TransformationFunctionParam": "YYYY-MM-DDTHH:mm:ss.fffZ",
    "RawDataPrimaryFieldMatchTerm": "__metadata___received",
    "RawDataPrimaryFieldComparisonType": 0,
    "RawDataSecondaryFieldMatchTerm": "",
    "RawDataSecondaryFieldComparisonType": 0,
    "RawDataThirdFieldMatchTerm": "",
    "RawDataThirdFieldComparisonType": 0,
    "IsArtifact": false,
    "ExtractionFunctionParam": "",
    "ExtractionFunction": 0,
    "CreationTimeUnixTimeInMs": 1623983029078,
    "ModificationTimeUnixTimeInMs": 1623983029078
  },
  {
    "Source": "FireEyeHelix",
    "Product": "FireEye Helix",
    "EventName": null,
    "SecurityEventFieldName": "EndTime",
    "TransformationFunction": 4,
    "TransformationFunctionParam": "YYYY-MM-DDTHH:mm:ss.fffZ",
    "RawDataPrimaryFieldMatchTerm": "__metadata___received",
    "RawDataPrimaryFieldComparisonType": 0,
    "RawDataSecondaryFieldMatchTerm": "",
    "RawDataSecondaryFieldComparisonType": 0,
    "RawDataThirdFieldMatchTerm": "",
    "RawDataThirdFieldComparisonType": 0,
    "IsArtifact": false,
    "ExtractionFunctionParam": "",
    "ExtractionFunction": 0,
    "CreationTimeUnixTimeInMs": 1623983029078,
    "ModificationTimeUnixTimeInMs": 1623983029078
  },
  {
    "Source": "FireEyeHelix",
    "Product": "FireEye Helix",
    "EventName": "netskope",
    "SecurityEventFieldName": "SourceUserName",
    "TransformationFunction": 0,
    "TransformationFunctionParam": "",
    "RawDataPrimaryFieldMatchTerm": "accountname",
    "RawDataPrimaryFieldComparisonType": 0,
    "RawDataSecondaryFieldMatchTerm": "logonid",
    "RawDataSecondaryFieldComparisonType": 0,
    "RawDataThirdFieldMatchTerm": "",
    "RawDataThirdFieldComparisonType": 0,
    "IsArtifact": false,
    "ExtractionFunctionParam": "",
    "ExtractionFunction": 0,
    "CreationTimeUnixTimeInMs": 1623983029078,
    "ModificationTimeUnixTimeInMs": 1623983029078
  },
  {
    "Source": "FireEyeHelix",
    "Product": "FireEye Helix",
    "EventName": "netskope",
    "SecurityEventFieldName": "SourceDomain",
    "TransformationFunction": 0,
    "TransformationFunctionParam": "",
    "RawDataPrimaryFieldMatchTerm": "srcdomain",
    "RawDataPrimaryFieldComparisonType": 0,
    "RawDataSecondaryFieldMatchTerm": "",
    "RawDataSecondaryFieldComparisonType": 0,
    "RawDataThirdFieldMatchTerm": "",
    "RawDataThirdFieldComparisonType": 0,
    "IsArtifact": true,
    "ExtractionFunctionParam": "",
    "ExtractionFunction": 0,
    "CreationTimeUnixTimeInMs": 1623983029078,
    "ModificationTimeUnixTimeInMs": 1623983029078
  },
  {
    "Source": "FireEyeHelix",
    "Product": "FireEye Helix",
    "EventName": "netskope",
    "SecurityEventFieldName": "DestinationDomain",
    "TransformationFunction": 0,
    "TransformationFunctionParam": "",
    "RawDataPrimaryFieldMatchTerm": "dstdomain",
    "RawDataPrimaryFieldComparisonType": 0,
    "RawDataSecondaryFieldMatchTerm": "",
    "RawDataSecondaryFieldComparisonType": 0,
    "RawDataThirdFieldMatchTerm": "",
    "RawDataThirdFieldComparisonType": 0,
    "IsArtifact": true,
    "ExtractionFunctionParam": "",
    "ExtractionFunction": 0,
    "CreationTimeUnixTimeInMs": 1623983029078,
    "ModificationTimeUnixTimeInMs": 1623983029078
  },
  {
    "Source": "FireEyeHelix",
    "Product": "FireEye Helix",
    "EventName": "netskope",
    "SecurityEventFieldName": "SourceAddress",
    "TransformationFunction": 0,
    "TransformationFunctionParam": "",
    "RawDataPrimaryFieldMatchTerm": "srcipv4",
    "RawDataPrimaryFieldComparisonType": 0,
    "RawDataSecondaryFieldMatchTerm": "",
    "RawDataSecondaryFieldComparisonType": 0,
    "RawDataThirdFieldMatchTerm": "",
    "RawDataThirdFieldComparisonType": 0,
    "IsArtifact": false,
    "ExtractionFunctionParam": "",
    "ExtractionFunction": 0,
    "CreationTimeUnixTimeInMs": 1623983029078,
    "ModificationTimeUnixTimeInMs": 1623983029078
  },
  {
    "Source": "FireEyeHelix",
    "Product": "FireEye Helix",
    "EventName": "netskope",
    "SecurityEventFieldName": "DestinationAddress",
    "TransformationFunction": 0,
    "TransformationFunctionParam": "",
    "RawDataPrimaryFieldMatchTerm": "dstipv4",
    "RawDataPrimaryFieldComparisonType": 0,
    "RawDataSecondaryFieldMatchTerm": "",
    "RawDataSecondaryFieldComparisonType": 0,
    "RawDataThirdFieldMatchTerm": "",
    "RawDataThirdFieldComparisonType": 0,
    "IsArtifact": false,
    "ExtractionFunctionParam": "",
    "ExtractionFunction": 0,
    "CreationTimeUnixTimeInMs": 1623983029078,
    "ModificationTimeUnixTimeInMs": 1623983029078
  },
  {
    "Source": "FireEyeHelix",
    "Product": "FireEye Helix",
    "EventName": "netskope",
    "SecurityEventFieldName": "GenericEntity",
    "TransformationFunction": 0,
    "TransformationFunctionParam": "",
    "RawDataPrimaryFieldMatchTerm": "object",
    "RawDataPrimaryFieldComparisonType": 0,
    "RawDataSecondaryFieldMatchTerm": "",
    "RawDataSecondaryFieldComparisonType": 0,
    "RawDataThirdFieldMatchTerm": "",
    "RawDataThirdFieldComparisonType": 0,
    "IsArtifact": false,
    "ExtractionFunctionParam": "",
    "ExtractionFunction": 0,
    "CreationTimeUnixTimeInMs": 1623983029078,
    "ModificationTimeUnixTimeInMs": 1623983029078
  },
  {
    "Source": "FireEyeHelix",
    "Product": "FireEye Helix",
    "EventName": "netskope",
    "SecurityEventFieldName": "SourceMacAddress",
    "TransformationFunction": 0,
    "TransformationFunctionParam": "",
    "RawDataPrimaryFieldMatchTerm": "srcmac",
    "RawDataPrimaryFieldComparisonType": 0,
    "RawDataSecondaryFieldMatchTerm": "",
    "RawDataSecondaryFieldComparisonType": 0,
    "RawDataThirdFieldMatchTerm": "",
    "RawDataThirdFieldComparisonType": 0,
    "IsArtifact": false,
    "ExtractionFunctionParam": "",
    "ExtractionFunction": 0,
    "CreationTimeUnixTimeInMs": 1623983029078,
    "ModificationTimeUnixTimeInMs": 1623983029078
  },
  {
    "Source": "FireEyeHelix",
    "Product": "FireEye Helix",
    "EventName": "netskope",
    "SecurityEventFieldName": "DestinationMacAddress",
    "TransformationFunction": 0,
    "TransformationFunctionParam": "",
    "RawDataPrimaryFieldMatchTerm": "dstmac",
    "RawDataPrimaryFieldComparisonType": 0,
    "RawDataSecondaryFieldMatchTerm": "",
    "RawDataSecondaryFieldComparisonType": 0,
    "RawDataThirdFieldMatchTerm": "",
    "RawDataThirdFieldComparisonType": 0,
    "IsArtifact": false,
    "ExtractionFunctionParam": "",
    "ExtractionFunction": 0,
    "CreationTimeUnixTimeInMs": 1623983029078,
    "ModificationTimeUnixTimeInMs": 1623983029078
  },
  {
    "Source": "FireEyeHelix",
    "Product": "FireEye Helix",
    "EventName": "netskope",
    "SecurityEventFieldName": "DestinationURL",
    "TransformationFunction": 0,
    "TransformationFunctionParam": "",
    "RawDataPrimaryFieldMatchTerm": "url",
    "RawDataPrimaryFieldComparisonType": 0,
    "RawDataSecondaryFieldMatchTerm": "",
    "RawDataSecondaryFieldComparisonType": 0,
    "RawDataThirdFieldMatchTerm": "",
    "RawDataThirdFieldComparisonType": 0,
    "IsArtifact": true,
    "ExtractionFunctionParam": "",
    "ExtractionFunction": 0,
    "CreationTimeUnixTimeInMs": 1623983029078,
    "ModificationTimeUnixTimeInMs": 1623983029078
  },
  {
    "Source": "FireEyeHelix",
    "Product": "FireEye Helix",
    "EventName": "netskope",
    "SecurityEventFieldName": "Name",
    "TransformationFunction": 0,
    "TransformationFunctionParam": "",
    "RawDataPrimaryFieldMatchTerm": "policy",
    "RawDataPrimaryFieldComparisonType": 0,
    "RawDataSecondaryFieldMatchTerm": "",
    "RawDataSecondaryFieldComparisonType": 0,
    "RawDataThirdFieldMatchTerm": "",
    "RawDataThirdFieldComparisonType": 0,
    "IsArtifact": false,
    "ExtractionFunctionParam": "",
    "ExtractionFunction": 0,
    "CreationTimeUnixTimeInMs": 1623983029078,
    "ModificationTimeUnixTimeInMs": 1623983029078
  },
  {
    "Source": "FireEyeHelix",
    "Product": "FireEye Helix",
    "EventName": "netskope",
    "SecurityEventFieldName": "CategoryOutcome",
    "TransformationFunction": 0,
    "TransformationFunctionParam": "",
    "RawDataPrimaryFieldMatchTerm": "activity",
    "RawDataPrimaryFieldComparisonType": 0,
    "RawDataSecondaryFieldMatchTerm": "",
    "RawDataSecondaryFieldComparisonType": 0,
    "RawDataThirdFieldMatchTerm": "",
    "RawDataThirdFieldComparisonType": 0,
    "IsArtifact": false,
    "ExtractionFunctionParam": "",
    "ExtractionFunction": 0,
    "CreationTimeUnixTimeInMs": 1623983029078,
    "ModificationTimeUnixTimeInMs": 1623983029078
  },
  {
    "Source": "FireEyeHelix",
    "Product": "FireEye Helix",
    "EventName": "fireeye",
    "SecurityEventFieldName": "SourceUserName",
    "TransformationFunction": 0,
    "TransformationFunctionParam": "",
    "RawDataPrimaryFieldMatchTerm": "targetusername",
    "RawDataPrimaryFieldComparisonType": 0,
    "RawDataSecondaryFieldMatchTerm": "",
    "RawDataSecondaryFieldComparisonType": 0,
    "RawDataThirdFieldMatchTerm": "",
    "RawDataThirdFieldComparisonType": 0,
    "IsArtifact": false,
    "ExtractionFunctionParam": "",
    "ExtractionFunction": 0,
    "CreationTimeUnixTimeInMs": 1623983029078,
    "ModificationTimeUnixTimeInMs": 1623983029078
  },
  {
    "Source": "FireEyeHelix",
    "Product": "FireEye Helix",
    "EventName": "fireeye",
    "SecurityEventFieldName": "DestinationUserName",
    "TransformationFunction": 0,
    "TransformationFunctionParam": "",
    "RawDataPrimaryFieldMatchTerm": "callingusername",
    "RawDataPrimaryFieldComparisonType": 0,
    "RawDataSecondaryFieldMatchTerm": "",
    "RawDataSecondaryFieldComparisonType": 0,
    "RawDataThirdFieldMatchTerm": "",
    "RawDataThirdFieldComparisonType": 0,
    "IsArtifact": false,
    "ExtractionFunctionParam": "",
    "ExtractionFunction": 0,
    "CreationTimeUnixTimeInMs": 1623983029078,
    "ModificationTimeUnixTimeInMs": 1623983029078
  },
  {
    "Source": "FireEyeHelix",
    "Product": "FireEye Helix",
    "EventName": "fireeye",
    "SecurityEventFieldName": "DestinationDomain",
    "TransformationFunction": 0,
    "TransformationFunctionParam": "",
    "RawDataPrimaryFieldMatchTerm": "dstdomain",
    "RawDataPrimaryFieldComparisonType": 0,
    "RawDataSecondaryFieldMatchTerm": "",
    "RawDataSecondaryFieldComparisonType": 0,
    "RawDataThirdFieldMatchTerm": "",
    "RawDataThirdFieldComparisonType": 0,
    "IsArtifact": true,
    "ExtractionFunctionParam": "",
    "ExtractionFunction": 0,
    "CreationTimeUnixTimeInMs": 1623983029078,
    "ModificationTimeUnixTimeInMs": 1623983029078
  },
  {
    "Source": "FireEyeHelix",
    "Product": "FireEye Helix",
    "EventName": "fireeye",
    "SecurityEventFieldName": "SourceAddress",
    "TransformationFunction": 0,
    "TransformationFunctionParam": "",
    "RawDataPrimaryFieldMatchTerm": "srcipv4",
    "RawDataPrimaryFieldComparisonType": 0,
    "RawDataSecondaryFieldMatchTerm": "",
    "RawDataSecondaryFieldComparisonType": 0,
    "RawDataThirdFieldMatchTerm": "",
    "RawDataThirdFieldComparisonType": 0,
    "IsArtifact": false,
    "ExtractionFunctionParam": "",
    "ExtractionFunction": 0,
    "CreationTimeUnixTimeInMs": 1623983029078,
    "ModificationTimeUnixTimeInMs": 1623983029078
  },
  {
    "Source": "FireEyeHelix",
    "Product": "FireEye Helix",
    "EventName": "fireeye",
    "SecurityEventFieldName": "DestinationAddress",
    "TransformationFunction": 0,
    "TransformationFunctionParam": "",
    "RawDataPrimaryFieldMatchTerm": "dstipv4",
    "RawDataPrimaryFieldComparisonType": 0,
    "RawDataSecondaryFieldMatchTerm": "",
    "RawDataSecondaryFieldComparisonType": 0,
    "RawDataThirdFieldMatchTerm": "",
    "RawDataThirdFieldComparisonType": 0,
    "IsArtifact": false,
    "ExtractionFunctionParam": "",
    "ExtractionFunction": 0,
    "CreationTimeUnixTimeInMs": 1623983029078,
    "ModificationTimeUnixTimeInMs": 1623983029078
  },
  {
    "Source": "FireEyeHelix",
    "Product": "FireEye Helix",
    "EventName": "fireeye",
    "SecurityEventFieldName": "GenericEntity",
    "TransformationFunction": 0,
    "TransformationFunctionParam": "",
    "RawDataPrimaryFieldMatchTerm": "virus",
    "RawDataPrimaryFieldComparisonType": 0,
    "RawDataSecondaryFieldMatchTerm": "",
    "RawDataSecondaryFieldComparisonType": 0,
    "RawDataThirdFieldMatchTerm": "",
    "RawDataThirdFieldComparisonType": 0,
    "IsArtifact": false,
    "ExtractionFunctionParam": "",
    "ExtractionFunction": 0,
    "CreationTimeUnixTimeInMs": 1623983029078,
    "ModificationTimeUnixTimeInMs": 1623983029078
  },
  {
    "Source": "FireEyeHelix",
    "Product": "FireEye Helix",
    "EventName": "fireeye",
    "SecurityEventFieldName": "SourceMacAddress",
    "TransformationFunction": 0,
    "TransformationFunctionParam": "",
    "RawDataPrimaryFieldMatchTerm": "srcmac",
    "RawDataPrimaryFieldComparisonType": 0,
    "RawDataSecondaryFieldMatchTerm": "",
    "RawDataSecondaryFieldComparisonType": 0,
    "RawDataThirdFieldMatchTerm": "",
    "RawDataThirdFieldComparisonType": 0,
    "IsArtifact": false,
    "ExtractionFunctionParam": "",
    "ExtractionFunction": 0,
    "CreationTimeUnixTimeInMs": 1623983029078,
    "ModificationTimeUnixTimeInMs": 1623983029078
  },
  {
    "Source": "FireEyeHelix",
    "Product": "FireEye Helix",
    "EventName": "fireeye",
    "SecurityEventFieldName": "DestinationMacAddress",
    "TransformationFunction": 0,
    "TransformationFunctionParam": "",
    "RawDataPrimaryFieldMatchTerm": "dstmac",
    "RawDataPrimaryFieldComparisonType": 0,
    "RawDataSecondaryFieldMatchTerm": "",
    "RawDataSecondaryFieldComparisonType": 0,
    "RawDataThirdFieldMatchTerm": "",
    "RawDataThirdFieldComparisonType": 0,
    "IsArtifact": false,
    "ExtractionFunctionParam": "",
    "ExtractionFunction": 0,
    "CreationTimeUnixTimeInMs": 1623983029078,
    "ModificationTimeUnixTimeInMs": 1623983029078
  },
  {
    "Source": "FireEyeHelix",
    "Product": "FireEye Helix",
    "EventName": "fireeye",
    "SecurityEventFieldName": "FileHash",
    "TransformationFunction": 0,
    "TransformationFunctionParam": "",
    "RawDataPrimaryFieldMatchTerm": "md5",
    "RawDataPrimaryFieldComparisonType": 0,
    "RawDataSecondaryFieldMatchTerm": "",
    "RawDataSecondaryFieldComparisonType": 0,
    "RawDataThirdFieldMatchTerm": "",
    "RawDataThirdFieldComparisonType": 0,
    "IsArtifact": true,
    "ExtractionFunctionParam": "",
    "ExtractionFunction": 0,
    "CreationTimeUnixTimeInMs": 1623983029078,
    "ModificationTimeUnixTimeInMs": 1623983029078
  },
  {
    "Source": "FireEyeHelix",
    "Product": "FireEye Helix",
    "EventName": "fireeye",
    "SecurityEventFieldName": "FileName",
    "TransformationFunction": 7,
    "TransformationFunctionParam": "([^\/]+$)",
    "RawDataPrimaryFieldMatchTerm": "filename",
    "RawDataPrimaryFieldComparisonType": 0,
    "RawDataSecondaryFieldMatchTerm": "",
    "RawDataSecondaryFieldComparisonType": 0,
    "RawDataThirdFieldMatchTerm": "",
    "RawDataThirdFieldComparisonType": 0,
    "IsArtifact": true,
    "ExtractionFunctionParam": "",
    "ExtractionFunction": 0,
    "CreationTimeUnixTimeInMs": 1623983029078,
    "ModificationTimeUnixTimeInMs": 1623983029078
  },
  {
    "Source": "FireEyeHelix",
    "Product": "FireEye Helix",
    "EventName": "fireeye",
    "SecurityEventFieldName": "Name",
    "TransformationFunction": 0,
    "TransformationFunctionParam": "",
    "RawDataPrimaryFieldMatchTerm": "eventname",
    "RawDataPrimaryFieldComparisonType": 0,
    "RawDataSecondaryFieldMatchTerm": "",
    "RawDataSecondaryFieldComparisonType": 0,
    "RawDataThirdFieldMatchTerm": "",
    "RawDataThirdFieldComparisonType": 0,
    "IsArtifact": false,
    "ExtractionFunctionParam": "",
    "ExtractionFunction": 0,
    "CreationTimeUnixTimeInMs": 1623983029078,
    "ModificationTimeUnixTimeInMs": 1623983029078
  },
  {
    "Source": "FireEyeHelix",
    "Product": "FireEye Helix",
    "EventName": "fireeye",
    "SecurityEventFieldName": "CategoryOutcome",
    "TransformationFunction": 0,
    "TransformationFunctionParam": "",
    "RawDataPrimaryFieldMatchTerm": "action",
    "RawDataPrimaryFieldComparisonType": 0,
    "RawDataSecondaryFieldMatchTerm": "",
    "RawDataSecondaryFieldComparisonType": 0,
    "RawDataThirdFieldMatchTerm": "",
    "RawDataThirdFieldComparisonType": 0,
    "IsArtifact": false,
    "ExtractionFunctionParam": "",
    "ExtractionFunction": 0,
    "CreationTimeUnixTimeInMs": 1623983029078,
    "ModificationTimeUnixTimeInMs": 1623983029078
  },
  {
    "Source": "FireEyeHelix",
    "Product": "FireEye Helix",
    "EventName": "fireeye",
    "SecurityEventFieldName": "DestinationPort",
    "TransformationFunction": 0,
    "TransformationFunctionParam": "",
    "RawDataPrimaryFieldMatchTerm": "dstport",
    "RawDataPrimaryFieldComparisonType": 0,
    "RawDataSecondaryFieldMatchTerm": "",
    "RawDataSecondaryFieldComparisonType": 0,
    "RawDataThirdFieldMatchTerm": "",
    "RawDataThirdFieldComparisonType": 0,
    "IsArtifact": false,
    "ExtractionFunctionParam": "",
    "ExtractionFunction": 0,
    "CreationTimeUnixTimeInMs": 1623983029078,
    "ModificationTimeUnixTimeInMs": 1623983029078
  },
  {
    "Source": "FireEyeHelix",
    "Product": "FireEye Helix",
    "EventName": "aws_guardduty",
    "SecurityEventFieldName": "SourceDomain",
    "TransformationFunction": 0,
    "TransformationFunctionParam": "",
    "RawDataPrimaryFieldMatchTerm": "domain",
    "RawDataPrimaryFieldComparisonType": 0,
    "RawDataSecondaryFieldMatchTerm": "",
    "RawDataSecondaryFieldComparisonType": 0,
    "RawDataThirdFieldMatchTerm": "",
    "RawDataThirdFieldComparisonType": 0,
    "IsArtifact": true,
    "ExtractionFunctionParam": ",",
    "ExtractionFunction": 0,
    "CreationTimeUnixTimeInMs": 1623983029078,
    "ModificationTimeUnixTimeInMs": 1623983029078
  },
  {
    "Source": "FireEyeHelix",
    "Product": "FireEye Helix",
    "EventName": "aws_guardduty",
    "SecurityEventFieldName": "Name",
    "TransformationFunction": 0,
    "TransformationFunctionParam": "",
    "RawDataPrimaryFieldMatchTerm": "eventtype",
    "RawDataPrimaryFieldComparisonType": 0,
    "RawDataSecondaryFieldMatchTerm": "",
    "RawDataSecondaryFieldComparisonType": 0,
    "RawDataThirdFieldMatchTerm": "",
    "RawDataThirdFieldComparisonType": 0,
    "IsArtifact": false,
    "ExtractionFunctionParam": "",
    "ExtractionFunction": 0,
    "CreationTimeUnixTimeInMs": 1623983029078,
    "ModificationTimeUnixTimeInMs": 1623983029078
  },
  {
    "Source": "FireEyeHelix",
    "Product": "FireEye Helix",
    "EventName": "aws_guardduty",
    "SecurityEventFieldName": "CategoryOutcome",
    "TransformationFunction": 0,
    "TransformationFunctionParam": "",
    "RawDataPrimaryFieldMatchTerm": "action",
    "RawDataPrimaryFieldComparisonType": 0,
    "RawDataSecondaryFieldMatchTerm": "",
    "RawDataSecondaryFieldComparisonType": 0,
    "RawDataThirdFieldMatchTerm": "",
    "RawDataThirdFieldComparisonType": 0,
    "IsArtifact": false,
    "ExtractionFunctionParam": "",
    "ExtractionFunction": 0,
    "CreationTimeUnixTimeInMs": 1623983029078,
    "ModificationTimeUnixTimeInMs": 1623983029078
  },
  {
    "Source": "FireEyeHelix",
    "Product": "FireEye Helix",
    "EventName": "crowdstrike_falconhost",
    "SecurityEventFieldName": "DestinationUserName",
    "TransformationFunction": 0,
    "TransformationFunctionParam": "",
    "RawDataPrimaryFieldMatchTerm": "targetusername",
    "RawDataPrimaryFieldComparisonType": 0,
    "RawDataSecondaryFieldMatchTerm": "",
    "RawDataSecondaryFieldComparisonType": 0,
    "RawDataThirdFieldMatchTerm": "",
    "RawDataThirdFieldComparisonType": 0,
    "IsArtifact": false,
    "ExtractionFunctionParam": "",
    "ExtractionFunction": 0,
    "CreationTimeUnixTimeInMs": 1623983029078,
    "ModificationTimeUnixTimeInMs": 1623983029078
  },
  {
    "Source": "FireEyeHelix",
    "Product": "FireEye Helix",
    "EventName": "crowdstrike_falconhost",
    "SecurityEventFieldName": "DestinationHostName",
    "TransformationFunction": 0,
    "TransformationFunctionParam": "",
    "RawDataPrimaryFieldMatchTerm": "dsthost",
    "RawDataPrimaryFieldComparisonType": 0,
    "RawDataSecondaryFieldMatchTerm": "",
    "RawDataSecondaryFieldComparisonType": 0,
    "RawDataThirdFieldMatchTerm": "",
    "RawDataThirdFieldComparisonType": 0,
    "IsArtifact": false,
    "ExtractionFunctionParam": "",
    "ExtractionFunction": 0,
    "CreationTimeUnixTimeInMs": 1623983029078,
    "ModificationTimeUnixTimeInMs": 1623983029078
  },
  {
    "Source": "FireEyeHelix",
    "Product": "FireEye Helix",
    "EventName": "crowdstrike_falconhost",
    "SecurityEventFieldName": "FileName",
    "TransformationFunction": 0,
    "TransformationFunctionParam": "",
    "RawDataPrimaryFieldMatchTerm": "filename",
    "RawDataPrimaryFieldComparisonType": 0,
    "RawDataSecondaryFieldMatchTerm": "",
    "RawDataSecondaryFieldComparisonType": 0,
    "RawDataThirdFieldMatchTerm": "",
    "RawDataThirdFieldComparisonType": 0,
    "IsArtifact": false,
    "ExtractionFunctionParam": "",
    "ExtractionFunction": 0,
    "CreationTimeUnixTimeInMs": 1623983029078,
    "ModificationTimeUnixTimeInMs": 1623983029078
  },
  {
    "Source": "FireEyeHelix",
    "Product": "FireEye Helix",
    "EventName": "crowdstrike_falconhost",
    "SecurityEventFieldName": "Message",
    "TransformationFunction": 0,
    "TransformationFunctionParam": "",
    "RawDataPrimaryFieldMatchTerm": "msg",
    "RawDataPrimaryFieldComparisonType": 0,
    "RawDataSecondaryFieldMatchTerm": "",
    "RawDataSecondaryFieldComparisonType": 0,
    "RawDataThirdFieldMatchTerm": "",
    "RawDataThirdFieldComparisonType": 0,
    "IsArtifact": false,
    "ExtractionFunctionParam": "",
    "ExtractionFunction": 0,
    "CreationTimeUnixTimeInMs": 1623983029078,
    "ModificationTimeUnixTimeInMs": 1623983029078
  },
  {
    "Source": "FireEyeHelix",
    "Product": "FireEye Helix",
    "EventName": "crowdstrike_falconhost",
    "SecurityEventFieldName": "Name",
    "TransformationFunction": 0,
    "TransformationFunctionParam": "",
    "RawDataPrimaryFieldMatchTerm": "ruleid",
    "RawDataPrimaryFieldComparisonType": 0,
    "RawDataSecondaryFieldMatchTerm": "",
    "RawDataSecondaryFieldComparisonType": 0,
    "RawDataThirdFieldMatchTerm": "",
    "RawDataThirdFieldComparisonType": 0,
    "IsArtifact": false,
    "ExtractionFunctionParam": "",
    "ExtractionFunction": 0,
    "CreationTimeUnixTimeInMs": 1623983029078,
    "ModificationTimeUnixTimeInMs": 1623983029078
  },
  {
    "Source": "FireEyeHelix",
    "Product": "FireEye Helix",
    "EventName": "ms_office365",
    "SecurityEventFieldName": "SourceUserName",
    "TransformationFunction": 0,
    "TransformationFunctionParam": "",
    "RawDataPrimaryFieldMatchTerm": "username",
    "RawDataPrimaryFieldComparisonType": 0,
    "RawDataSecondaryFieldMatchTerm": "",
    "RawDataSecondaryFieldComparisonType": 0,
    "RawDataThirdFieldMatchTerm": "",
    "RawDataThirdFieldComparisonType": 0,
    "IsArtifact": false,
    "ExtractionFunctionParam": "",
    "ExtractionFunction": 0,
    "CreationTimeUnixTimeInMs": 1623983029078,
    "ModificationTimeUnixTimeInMs": 1623983029078
  },
  {
    "Source": "FireEyeHelix",
    "Product": "FireEye Helix",
    "EventName": "ms_office365",
    "SecurityEventFieldName": "SourceDomain",
    "TransformationFunction": 0,
    "TransformationFunctionParam": "",
    "RawDataPrimaryFieldMatchTerm": "srcdomain",
    "RawDataPrimaryFieldComparisonType": 0,
    "RawDataSecondaryFieldMatchTerm": "",
    "RawDataSecondaryFieldComparisonType": 0,
    "RawDataThirdFieldMatchTerm": "",
    "RawDataThirdFieldComparisonType": 0,
    "IsArtifact": true,
    "ExtractionFunctionParam": "",
    "ExtractionFunction": 0,
    "CreationTimeUnixTimeInMs": 1623983029078,
    "ModificationTimeUnixTimeInMs": 1623983029078
  },
  {
    "Source": "FireEyeHelix",
    "Product": "FireEye Helix",
    "EventName": "ms_office365",
    "SecurityEventFieldName": "DestinationDomain",
    "TransformationFunction": 0,
    "TransformationFunctionParam": "",
    "RawDataPrimaryFieldMatchTerm": "dstdomain",
    "RawDataPrimaryFieldComparisonType": 0,
    "RawDataSecondaryFieldMatchTerm": "",
    "RawDataSecondaryFieldComparisonType": 0,
    "RawDataThirdFieldMatchTerm": "",
    "RawDataThirdFieldComparisonType": 0,
    "IsArtifact": true,
    "ExtractionFunctionParam": "",
    "ExtractionFunction": 0,
    "CreationTimeUnixTimeInMs": 1623983029078,
    "ModificationTimeUnixTimeInMs": 1623983029078
  },
  {
    "Source": "FireEyeHelix",
    "Product": "FireEye Helix",
    "EventName": "ms_office365",
    "SecurityEventFieldName": "SourceAddress",
    "TransformationFunction": 0,
    "TransformationFunctionParam": "",
    "RawDataPrimaryFieldMatchTerm": "srcipv4",
    "RawDataPrimaryFieldComparisonType": 0,
    "RawDataSecondaryFieldMatchTerm": "",
    "RawDataSecondaryFieldComparisonType": 0,
    "RawDataThirdFieldMatchTerm": "",
    "RawDataThirdFieldComparisonType": 0,
    "IsArtifact": false,
    "ExtractionFunctionParam": "",
    "ExtractionFunction": 0,
    "CreationTimeUnixTimeInMs": 1623983029078,
    "ModificationTimeUnixTimeInMs": 1623983029078
  },
  {
    "Source": "FireEyeHelix",
    "Product": "FireEye Helix",
    "EventName": "ms_office365",
    "SecurityEventFieldName": "DestinationAddress",
    "TransformationFunction": 0,
    "TransformationFunctionParam": "",
    "RawDataPrimaryFieldMatchTerm": "dstipv4",
    "RawDataPrimaryFieldComparisonType": 0,
    "RawDataSecondaryFieldMatchTerm": "",
    "RawDataSecondaryFieldComparisonType": 0,
    "RawDataThirdFieldMatchTerm": "",
    "RawDataThirdFieldComparisonType": 0,
    "IsArtifact": false,
    "ExtractionFunctionParam": "",
    "ExtractionFunction": 0,
    "CreationTimeUnixTimeInMs": 1623983029078,
    "ModificationTimeUnixTimeInMs": 1623983029078
  },
  {
    "Source": "FireEyeHelix",
    "Product": "FireEye Helix",
    "EventName": "ms_office365",
    "SecurityEventFieldName": "Name",
    "TransformationFunction": 0,
    "TransformationFunctionParam": "",
    "RawDataPrimaryFieldMatchTerm": "metaclass",
    "RawDataPrimaryFieldComparisonType": 0,
    "RawDataSecondaryFieldMatchTerm": "",
    "RawDataSecondaryFieldComparisonType": 0,
    "RawDataThirdFieldMatchTerm": "",
    "RawDataThirdFieldComparisonType": 0,
    "IsArtifact": false,
    "ExtractionFunctionParam": "",
    "ExtractionFunction": 0,
    "CreationTimeUnixTimeInMs": 1623983029078,
    "ModificationTimeUnixTimeInMs": 1623983029078
  },
  {
    "Source": "FireEyeHelix",
    "Product": "FireEye Helix",
    "EventName": "ms_office365",
    "SecurityEventFieldName": "CategoryOutcome",
    "TransformationFunction": 0,
    "TransformationFunctionParam": "",
    "RawDataPrimaryFieldMatchTerm": "action",
    "RawDataPrimaryFieldComparisonType": 0,
    "RawDataSecondaryFieldMatchTerm": "",
    "RawDataSecondaryFieldComparisonType": 0,
    "RawDataThirdFieldMatchTerm": "",
    "RawDataThirdFieldComparisonType": 0,
    "IsArtifact": false,
    "ExtractionFunctionParam": "",
    "ExtractionFunction": 0,
    "CreationTimeUnixTimeInMs": 1623983029078,
    "ModificationTimeUnixTimeInMs": 1623983029078
  },
  {
    "Source": "FireEyeHelix",
    "Product": "FireEye Helix",
    "EventName": "intel_hit",
    "SecurityEventFieldName": "Name",
    "TransformationFunction": 0,
    "TransformationFunctionParam": "",
    "RawDataPrimaryFieldMatchTerm": "eventtype",
    "RawDataPrimaryFieldComparisonType": 0,
    "RawDataSecondaryFieldMatchTerm": "",
    "RawDataSecondaryFieldComparisonType": 0,
    "RawDataThirdFieldMatchTerm": "",
    "RawDataThirdFieldComparisonType": 0,
    "IsArtifact": false,
    "ExtractionFunctionParam": "",
    "ExtractionFunction": 0,
    "CreationTimeUnixTimeInMs": 1623983029078,
    "ModificationTimeUnixTimeInMs": 1623983029078
  },
  {
    "Source": "FireEyeHelix",
    "Product": "FireEye Helix",
    "EventName": "intel_hit",
    "SecurityEventFieldName": "CategoryOutcome",
    "TransformationFunction": 0,
    "TransformationFunctionParam": "",
    "RawDataPrimaryFieldMatchTerm": "action",
    "RawDataPrimaryFieldComparisonType": 0,
    "RawDataSecondaryFieldMatchTerm": "",
    "RawDataSecondaryFieldComparisonType": 0,
    "RawDataThirdFieldMatchTerm": "",
    "RawDataThirdFieldComparisonType": 0,
    "IsArtifact": false,
    "ExtractionFunctionParam": "",
    "ExtractionFunction": 0,
    "CreationTimeUnixTimeInMs": 1623983029078,
    "ModificationTimeUnixTimeInMs": 1623983029078
  },
  {
    "Source": "FireEyeHelix",
    "Product": "FireEye Helix",
    "EventName": "zimperium",
    "SecurityEventFieldName": "SourceUserName",
    "TransformationFunction": 0,
    "TransformationFunctionParam": "",
    "RawDataPrimaryFieldMatchTerm": "username",
    "RawDataPrimaryFieldComparisonType": 0,
    "RawDataSecondaryFieldMatchTerm": "",
    "RawDataSecondaryFieldComparisonType": 0,
    "RawDataThirdFieldMatchTerm": "",
    "RawDataThirdFieldComparisonType": 0,
    "IsArtifact": false,
    "ExtractionFunctionParam": "",
    "ExtractionFunction": 0,
    "CreationTimeUnixTimeInMs": 1623983029078,
    "ModificationTimeUnixTimeInMs": 1623983029078
  },
  {
    "Source": "FireEyeHelix",
    "Product": "FireEye Helix",
    "EventName": "zimperium",
    "SecurityEventFieldName": "DestinationAddress",
    "TransformationFunction": 0,
    "TransformationFunctionParam": "",
    "RawDataPrimaryFieldMatchTerm": "dstipv4",
    "RawDataPrimaryFieldComparisonType": 0,
    "RawDataSecondaryFieldMatchTerm": "",
    "RawDataSecondaryFieldComparisonType": 0,
    "RawDataThirdFieldMatchTerm": "",
    "RawDataThirdFieldComparisonType": 0,
    "IsArtifact": false,
    "ExtractionFunctionParam": "",
    "ExtractionFunction": 0,
    "CreationTimeUnixTimeInMs": 1623983029078,
    "ModificationTimeUnixTimeInMs": 1623983029078
  },
  {
    "Source": "FireEyeHelix",
    "Product": "FireEye Helix",
    "EventName": "zimperium",
    "SecurityEventFieldName": "Name",
    "TransformationFunction": 0,
    "TransformationFunctionParam": "",
    "RawDataPrimaryFieldMatchTerm": "threat",
    "RawDataPrimaryFieldComparisonType": 0,
    "RawDataSecondaryFieldMatchTerm": "",
    "RawDataSecondaryFieldComparisonType": 0,
    "RawDataThirdFieldMatchTerm": "",
    "RawDataThirdFieldComparisonType": 0,
    "IsArtifact": false,
    "ExtractionFunctionParam": "",
    "ExtractionFunction": 0,
    "CreationTimeUnixTimeInMs": 1623983029078,
    "ModificationTimeUnixTimeInMs": 1623983029078
  },
  {
    "Source": "FireEyeHelix",
    "Product": "FireEye Helix",
    "EventName": "zimperium",
    "SecurityEventFieldName": "CategoryOutcome",
    "TransformationFunction": 0,
    "TransformationFunctionParam": "",
    "RawDataPrimaryFieldMatchTerm": "action",
    "RawDataPrimaryFieldComparisonType": 0,
    "RawDataSecondaryFieldMatchTerm": "",
    "RawDataSecondaryFieldComparisonType": 0,
    "RawDataThirdFieldMatchTerm": "",
    "RawDataThirdFieldComparisonType": 0,
    "IsArtifact": false,
    "ExtractionFunctionParam": "",
    "ExtractionFunction": 0,
    "CreationTimeUnixTimeInMs": 1623983029078,
    "ModificationTimeUnixTimeInMs": 1623983029078
  },
  {
    "Source": "FireEyeHelix",
    "Product": "FireEye Helix",
    "EventName": "analytics_beta",
    "SecurityEventFieldName": "SourceUserName",
    "TransformationFunction": 0,
    "TransformationFunctionParam": "",
    "RawDataPrimaryFieldMatchTerm": "username",
    "RawDataPrimaryFieldComparisonType": 0,
    "RawDataSecondaryFieldMatchTerm": "",
    "RawDataSecondaryFieldComparisonType": 0,
    "RawDataThirdFieldMatchTerm": "",
    "RawDataThirdFieldComparisonType": 0,
    "IsArtifact": false,
    "ExtractionFunctionParam": "",
    "ExtractionFunction": 0,
    "CreationTimeUnixTimeInMs": 1623983029078,
    "ModificationTimeUnixTimeInMs": 1623983029078
  },
  {
    "Source": "FireEyeHelix",
    "Product": "FireEye Helix",
    "EventName": "analytics_beta",
    "SecurityEventFieldName": "SourceDomain",
    "TransformationFunction": 0,
    "TransformationFunctionParam": "",
    "RawDataPrimaryFieldMatchTerm": "srcdomain",
    "RawDataPrimaryFieldComparisonType": 0,
    "RawDataSecondaryFieldMatchTerm": "",
    "RawDataSecondaryFieldComparisonType": 0,
    "RawDataThirdFieldMatchTerm": "",
    "RawDataThirdFieldComparisonType": 0,
    "IsArtifact": true,
    "ExtractionFunctionParam": "",
    "ExtractionFunction": 0,
    "CreationTimeUnixTimeInMs": 1623983029078,
    "ModificationTimeUnixTimeInMs": 1623983029078
  },
  {
    "Source": "FireEyeHelix",
    "Product": "FireEye Helix",
    "EventName": "analytics_beta",
    "SecurityEventFieldName": "SourceAddress",
    "TransformationFunction": 0,
    "TransformationFunctionParam": "",
    "RawDataPrimaryFieldMatchTerm": "srcipv4",
    "RawDataPrimaryFieldComparisonType": 0,
    "RawDataSecondaryFieldMatchTerm": "",
    "RawDataSecondaryFieldComparisonType": 0,
    "RawDataThirdFieldMatchTerm": "",
    "RawDataThirdFieldComparisonType": 0,
    "IsArtifact": false,
    "ExtractionFunctionParam": "",
    "ExtractionFunction": 0,
    "CreationTimeUnixTimeInMs": 1623983029078,
    "ModificationTimeUnixTimeInMs": 1623983029078
  },
  {
    "Source": "FireEyeHelix",
    "Product": "FireEye Helix",
    "EventName": "analytics_beta",
    "SecurityEventFieldName": "SourceAddress",
    "TransformationFunction": 0,
    "TransformationFunctionParam": "",
    "RawDataPrimaryFieldMatchTerm": "srcipv4",
    "RawDataPrimaryFieldComparisonType": 0,
    "RawDataSecondaryFieldMatchTerm": "",
    "RawDataSecondaryFieldComparisonType": 0,
    "RawDataThirdFieldMatchTerm": "",
    "RawDataThirdFieldComparisonType": 0,
    "IsArtifact": false,
    "ExtractionFunctionParam": "",
    "ExtractionFunction": 0,
    "CreationTimeUnixTimeInMs": 1623983029078,
    "ModificationTimeUnixTimeInMs": 1623983029078
  },
  {
    "Source": "FireEyeHelix",
    "Product": "FireEye Helix",
    "EventName": "analytics_beta",
    "SecurityEventFieldName": "Name",
    "TransformationFunction": 0,
    "TransformationFunctionParam": "",
    "RawDataPrimaryFieldMatchTerm": "application",
    "RawDataPrimaryFieldComparisonType": 0,
    "RawDataSecondaryFieldMatchTerm": "",
    "RawDataSecondaryFieldComparisonType": 0,
    "RawDataThirdFieldMatchTerm": "",
    "RawDataThirdFieldComparisonType": 0,
    "IsArtifact": false,
    "ExtractionFunctionParam": "",
    "ExtractionFunction": 0,
    "CreationTimeUnixTimeInMs": 1623983029078,
    "ModificationTimeUnixTimeInMs": 1623983029078
  },
  {
    "Source": "FireEyeHelix",
    "Product": "FireEye Helix",
    "EventName": "ms_windows_event",
    "SecurityEventFieldName": "SourceUserName",
    "TransformationFunction": 0,
    "TransformationFunctionParam": "",
    "RawDataPrimaryFieldMatchTerm": "username",
    "RawDataPrimaryFieldComparisonType": 0,
    "RawDataSecondaryFieldMatchTerm": "",
    "RawDataSecondaryFieldComparisonType": 0,
    "RawDataThirdFieldMatchTerm": "",
    "RawDataThirdFieldComparisonType": 0,
    "IsArtifact": false,
    "ExtractionFunctionParam": "",
    "ExtractionFunction": 0,
    "CreationTimeUnixTimeInMs": 1623983029078,
    "ModificationTimeUnixTimeInMs": 1623983029078
  },
  {
    "Source": "FireEyeHelix",
    "Product": "FireEye Helix",
    "EventName": "ms_windows_event",
    "SecurityEventFieldName": "SourceHostName",
    "TransformationFunction": 0,
    "TransformationFunctionParam": "",
    "RawDataPrimaryFieldMatchTerm": "domain",
    "RawDataPrimaryFieldComparisonType": 0,
    "RawDataSecondaryFieldMatchTerm": "",
    "RawDataSecondaryFieldComparisonType": 0,
    "RawDataThirdFieldMatchTerm": "",
    "RawDataThirdFieldComparisonType": 0,
    "IsArtifact": false,
    "ExtractionFunctionParam": "",
    "ExtractionFunction": 0,
    "CreationTimeUnixTimeInMs": 1623983029078,
    "ModificationTimeUnixTimeInMs": 1623983029078
  },
  {
    "Source": "FireEyeHelix",
    "Product": "FireEye Helix",
    "EventName": "ms_windows_event",
    "SecurityEventFieldName": "SourceProcessName",
    "TransformationFunction": 0,
    "TransformationFunctionParam": "",
    "RawDataPrimaryFieldMatchTerm": "process",
    "RawDataPrimaryFieldComparisonType": 0,
    "RawDataSecondaryFieldMatchTerm": "",
    "RawDataSecondaryFieldComparisonType": 0,
    "RawDataThirdFieldMatchTerm": "",
    "RawDataThirdFieldComparisonType": 0,
    "IsArtifact": true,
    "ExtractionFunctionParam": "",
    "ExtractionFunction": 0,
    "CreationTimeUnixTimeInMs": 1623983029078,
    "ModificationTimeUnixTimeInMs": 1623983029078
  },
  {
    "Source": "FireEyeHelix",
    "Product": "FireEye Helix",
    "EventName": "ms_windows_event",
    "SecurityEventFieldName": "Name",
    "TransformationFunction": 0,
    "TransformationFunctionParam": "",
    "RawDataPrimaryFieldMatchTerm": "service",
    "RawDataPrimaryFieldComparisonType": 0,
    "RawDataSecondaryFieldMatchTerm": "",
    "RawDataSecondaryFieldComparisonType": 0,
    "RawDataThirdFieldMatchTerm": "",
    "RawDataThirdFieldComparisonType": 0,
    "IsArtifact": false,
    "ExtractionFunctionParam": "",
    "ExtractionFunction": 0,
    "CreationTimeUnixTimeInMs": 1623983029078,
    "ModificationTimeUnixTimeInMs": 1623983029078
  },
  {
    "Source": "FireEyeHelix",
    "Product": "FireEye Helix",
    "EventName": "fireeye_nx_alert",
    "SecurityEventFieldName": "SourceUserName",
    "TransformationFunction": 0,
    "TransformationFunctionParam": "",
    "RawDataPrimaryFieldMatchTerm": "type_details_user",
    "RawDataPrimaryFieldComparisonType": 0,
    "RawDataSecondaryFieldMatchTerm": "",
    "RawDataSecondaryFieldComparisonType": 0,
    "RawDataThirdFieldMatchTerm": "",
    "RawDataThirdFieldComparisonType": 0,
    "IsArtifact": false,
    "ExtractionFunctionParam": "",
    "ExtractionFunction": 0,
    "CreationTimeUnixTimeInMs": 1623983029078,
    "ModificationTimeUnixTimeInMs": 1623983029078
  },
  {
    "Source": "FireEyeHelix",
    "Product": "FireEye Helix",
    "EventName": "fireeye_nx_alert",
    "SecurityEventFieldName": "SourceHostName",
    "TransformationFunction": 0,
    "TransformationFunctionParam": "",
    "RawDataPrimaryFieldMatchTerm": "type_details_host",
    "RawDataPrimaryFieldComparisonType": 0,
    "RawDataSecondaryFieldMatchTerm": "",
    "RawDataSecondaryFieldComparisonType": 0,
    "RawDataThirdFieldMatchTerm": "",
    "RawDataThirdFieldComparisonType": 0,
    "IsArtifact": false,
    "ExtractionFunctionParam": "",
    "ExtractionFunction": 0,
    "CreationTimeUnixTimeInMs": 1623983029078,
    "ModificationTimeUnixTimeInMs": 1623983029078
  },
  {
    "Source": "FireEyeHelix",
    "Product": "FireEye Helix",
    "EventName": "fireeye_nx_alert",
    "SecurityEventFieldName": "FileName",
    "TransformationFunction": 7,
    "TransformationFunctionParam": "([^\/]+$)",
    "RawDataPrimaryFieldMatchTerm": "filename",
    "RawDataPrimaryFieldComparisonType": 0,
    "RawDataSecondaryFieldMatchTerm": "",
    "RawDataSecondaryFieldComparisonType": 0,
    "RawDataThirdFieldMatchTerm": "",
    "RawDataThirdFieldComparisonType": 0,
    "IsArtifact": true,
    "ExtractionFunctionParam": "",
    "ExtractionFunction": 0,
    "CreationTimeUnixTimeInMs": 1623983029078,
    "ModificationTimeUnixTimeInMs": 1623983029078
  },
  {
    "Source": "FireEyeHelix",
    "Product": "FireEye Helix",
    "EventName": "fireeye_nx_alert",
    "SecurityEventFieldName": "Name",
    "TransformationFunction": 0,
    "TransformationFunctionParam": "",
    "RawDataPrimaryFieldMatchTerm": "eventtype",
    "RawDataPrimaryFieldComparisonType": 0,
    "RawDataSecondaryFieldMatchTerm": "",
    "RawDataSecondaryFieldComparisonType": 0,
    "RawDataThirdFieldMatchTerm": "",
    "RawDataThirdFieldComparisonType": 0,
    "IsArtifact": false,
    "ExtractionFunctionParam": "",
    "ExtractionFunction": 0,
    "CreationTimeUnixTimeInMs": 1623983029078,
    "ModificationTimeUnixTimeInMs": 1623983029078
  },
  {
    "Source": "FireEyeHelix",
    "Product": "FireEye Helix",
    "EventName": "fireeye_nx_alert",
    "SecurityEventFieldName": "CategoryOutcome",
    "TransformationFunction": 0,
    "TransformationFunctionParam": "",
    "RawDataPrimaryFieldMatchTerm": "status",
    "RawDataPrimaryFieldComparisonType": 0,
    "RawDataSecondaryFieldMatchTerm": "",
    "RawDataSecondaryFieldComparisonType": 0,
    "RawDataThirdFieldMatchTerm": "",
    "RawDataThirdFieldComparisonType": 0,
    "IsArtifact": false,
    "ExtractionFunctionParam": "",
    "ExtractionFunction": 0,
    "CreationTimeUnixTimeInMs": 1623983029078,
    "ModificationTimeUnixTimeInMs": 1623983029078
  }
]